bit_by_mail/__init__.py
bit_by_mail/cli.py
bit_by_mail/frontend/dist/658.48e63505b294a5f13f94.js
bit_by_mail/frontend/dist/658.48e63505b294a5f13f94.js.LICENSE.txt
bit_by_mail/frontend/dist/658.48e63505b294a5f13f94.js.map
bit_by_mail/frontend/dist/77.80bc453f3abcfb5d9110.js
bit_by_mail/frontend/dist/77.80bc453f3abcfb5d9110.js.LICENSE.txt
bit_by_mail/frontend/dist/77.80bc453f3abcfb5d9110.js.map
bit_by_mail/frontend/dist/95650af64c39680dad61.ttf
bit_by_mail/frontend/dist/editor.worker.js
bit_by_mail/frontend/dist/editor.worker.js.map
bit_by_mail/frontend/dist/html.worker.js
bit_by_mail/frontend/dist/html.worker.js.map
bit_by_mail/frontend/dist/index.html
bit_by_mail/frontend/dist/main.23a84a6facd7c040305a.js
bit_by_mail/frontend/dist/main.23a84a6facd7c040305a.js.LICENSE.txt
bit_by_mail/frontend/dist/main.23a84a6facd7c040305a.js.map
bit_by_mail/frontend/dist/main.css
bit_by_mail/frontend/dist/main.css.map
bit_by_mail/server/server.py
bit_by_mail/server/handlers/attachment_handler.py
bit_by_mail/server/handlers/websocket_handler.py
bit_by_mail/server/services/campaign_service.py
bit_by_mail/server/services/config_service.py
bit_by_mail/server/services/crypto_service.py
bit_by_mail/server/services/mailer_service.py
bit_by_mail/server/services/preflight_service.py
bit_by_mail/server/services/recipient_service.py
bit_by_mail/server/services/settings_service.py
bit_by_mail/server/services/template_service.py
bit_by_mail-1.0.0.dist-info/METADATA
bit_by_mail-1.0.0.dist-info/WHEEL
bit_by_mail-1.0.0.dist-info/entry_points.txt
bit_by_mail-1.0.0.dist-info/top_level.txt
bit_by_mail-1.0.0.dist-info/RECORD
