Metadata-Version: 2.4
Name: bit-by-mail
Version: 1.0.0
Summary: A simple, self-hosted bulk mailing application with a web-based UI.
Author-email: Aditya Godse <adimail2404@gmail.com>
License: MIT
Project-URL: Homepage, https://github.com/IOIT-ACM/bit-by-mail
Classifier: Programming Language :: Python :: 3
Classifier: License :: OSI Approved :: MIT License
Classifier: Operating System :: OS Independent
Classifier: Topic :: Communications :: Email
Requires-Python: >=3.9
Requires-Dist: tornado>=6.4
Requires-Dist: pandas>=2.0.0
Requires-Dist: cryptography>=42.0.0
